jxImgTools-0.4.4.data/scripts/jxImgTools_setup
jximgtools/__init__.py
jximgtools/demo.py
jximgtools/imgIO.py
jximgtools/metric.py
jximgtools/utils.py
jximgtools/process/__init__.py
jximgtools/process/imgProcess.py
jximgtools/visualization/__init__.py
jximgtools/visualization/volSlicer.py
jxImgTools-0.4.4.dist-info/METADATA
jxImgTools-0.4.4.dist-info/WHEEL
jxImgTools-0.4.4.dist-info/top_level.txt
jxImgTools-0.4.4.dist-info/RECORD
