Metadata-Version: 2.1
Name: jxImgTools
Version: 0.4.4
Summary: Image utility functions for personal use
Home-page: https://github.com/jr-xing/jxImgTools
Author: Jerry Xing
Author-email: j.xing.www@gmail.com
License: UNKNOWN
Platform: UNKNOWN
Requires-Dist: numpy
Requires-Dist: scipy
Requires-Dist: matplotlib
Requires-Dist: SimpleITK
